seawave_retracking/__init__.py
seawave_retracking/backscattering.py
seawave_retracking/brown.py
seawave_retracking/config.toml
seawave_retracking/pulses.py
seawave_retracking-1.0.3.dist-info/LICENSE
seawave_retracking-1.0.3.dist-info/METADATA
seawave_retracking-1.0.3.dist-info/WHEEL
seawave_retracking-1.0.3.dist-info/top_level.txt
seawave_retracking-1.0.3.dist-info/version.txt
seawave_retracking-1.0.3.dist-info/RECORD
