Metadata-Version: 2.1
Name: seawave-retracking
Version: 1.0.3
Summary: UNKNOWN
Home-page: UNKNOWN
Author: Kirill Ponur
Author-email: ponur@ipfran.ru
License: UNKNOWN
Platform: UNKNOWN
Classifier: Programming Language :: Python :: 3
Classifier: License :: OSI Approved :: GNU General Public License v3 (GPLv3)
Classifier: Operating System :: OS Independent
Requires-Python: >=3.6
License-File: LICENSE
Requires-Dist: numpy
Requires-Dist: scipy
Requires-Dist: toml
Requires-Dist: pandas
Requires-Dist: openpyxl
